CHANGES
LICENSE
README
ez_setup.py
setup.py
IMDbName.egg-info/PKG-INFO
IMDbName.egg-info/SOURCES.txt
IMDbName.egg-info/dependency_links.txt
IMDbName.egg-info/entry_points.txt
IMDbName.egg-info/requires.txt
IMDbName.egg-info/top_level.txt
imdbname/__init__.py
imdbname/imdbname.py