Metadata-Version: 1.0
Name: IMDbName
Version: 0.1
Summary: A script for renaming movies using the IMDb database
Home-page: https://svn.jetheis.com/public/IMDbName/trunk
Author: Jimmy Theis
Author-email: jimmy@jetheis.com
License: GPLv3
Keywords: script imdb movie rename database
Platform: UNKNOWN
